tacost/__init__.py
tacost/__main__.py
tacost/calculate_toa.py
tacost/make_positions.py
tacost/make_sim_audio.py
tacost/make_source_sounds.py
tacost/making_point_grid.py
tacost/making_sim_recordings.py
tacost/simulate_LMU_playback_setup.py
tacost/tests/__init__.py
tacost/tests/test_check_paramfile_works.py
tacost/tests/test_main.py
tacost/tests/test_make_positions.py
tacost/tests/test_make_sim_audio.py
tacost/tests/test_toa.py
tacost/tests/tests_calculate_toa.py
tacost-0.1.35.dist-info/LICENSE
tacost-0.1.35.dist-info/METADATA
tacost-0.1.35.dist-info/WHEEL
tacost-0.1.35.dist-info/top_level.txt
tacost-0.1.35.dist-info/RECORD
