Metadata-Version: 2.1
Name: tacost
Version: 0.1.35
Summary: tact: Test ACoustic Tracking: Create simulated sound sources/ trajectories to test the accuracy of an acoustic tracking system
Home-page: https://github.com/thejasvibr/test_acoustictracking.git
Author: Thejasvi Beleyur
Author-email: thejasvib@gmail.com
License: MIT
Platform: UNKNOWN
Classifier: Development Status :: 2 - Pre-Alpha
Classifier: License :: OSI Approved :: MIT License
Classifier: Programming Language :: Python
Classifier: Programming Language :: Python :: 3.5
Classifier: Programming Language :: Python :: 3.6
Classifier: Topic :: Software Development :: Libraries
Classifier: Topic :: Software Development :: Libraries :: Python Modules
Classifier: Intended Audience :: Science/Research
Requires-Python: >=3.5
Requires-Dist: numpy
Requires-Dist: pandas
Requires-Dist: pyyaml
Requires-Dist: scipy
